gpt4_copilot_free_api-0.1.3.dist-info/METADATA
gpt4_copilot_free_api-0.1.3.dist-info/WHEEL
gpt4_copilot_free_api-0.1.3.dist-info/entry_points.txt
gpt4_copilot_free_api/__init__.py
gpt4_copilot_free_api/api.py
gpt4_copilot_free_api/free-gpt4.py
gpt4_copilot_free_api/server.py
gpt4_copilot_free_api-0.1.3.dist-info/RECORD
